quantile_regression_pdlp/__init__.py
quantile_regression_pdlp/quantile_regression.py
quantile_regression_pdlp-0.1.1.dist-info/licenses/LICENSE
quantile_regression_pdlp-0.1.1.dist-info/METADATA
quantile_regression_pdlp-0.1.1.dist-info/WHEEL
quantile_regression_pdlp-0.1.1.dist-info/top_level.txt
quantile_regression_pdlp-0.1.1.dist-info/RECORD
