Metadata-Version: 2.4
Name: quantile-regression-pdlp
Version: 0.1.1
Summary: Quantile regression via linear programming using Google OR-Tools PDLP, with a scikit-learn compatible API and statistical summaries.
Author: Joshua Vernazza
License: MIT
Project-URL: Repository, https://github.com/joshvern/quantile_regression_pdlp
Project-URL: Issues, https://github.com/joshvern/quantile_regression_pdlp/issues
Project-URL: Documentation, https://joshvern.github.io/quantile_regression_pdlp/
Keywords: quantile-regression,linear-programming,optimization,pdlp,ortools,statistics,machine-learning
Classifier: License :: OSI Approved :: MIT License
Classifier: Programming Language :: Python :: 3
Classifier: Programming Language :: Python :: 3 :: Only
Classifier: Programming Language :: Python :: 3.9
Classifier: Programming Language :: Python :: 3.10
Classifier: Programming Language :: Python :: 3.11
Classifier: Operating System :: OS Independent
Requires-Python: >=3.9
License-File: LICENSE
Requires-Dist: ortools>=9.0.9047
Requires-Dist: numpy>=1.18.0
Requires-Dist: pandas>=1.0.0
Requires-Dist: scipy>=1.4.0
Requires-Dist: tqdm>=4.50.0
Requires-Dist: joblib>=1.0.0
Requires-Dist: scikit-learn>=0.22.0
Provides-Extra: test
Requires-Dist: pytest>=7; extra == "test"
Dynamic: license-file
